bmpy/__init__.py
bmpy/bmpy.py
bmpy-1.0.0.dist-info/LICENSE
bmpy-1.0.0.dist-info/METADATA
bmpy-1.0.0.dist-info/WHEEL
bmpy-1.0.0.dist-info/entry_points.txt
bmpy-1.0.0.dist-info/top_level.txt
bmpy-1.0.0.dist-info/RECORD
