Metadata-Version: 2.1
Name: bmpy
Version: 1.0.0
Summary: Bounty Meter is a command-line utility tool designed for bug bounty hunters to define their bounty target for a year, maintain and keep record of their bounties on a monthly basis, and track their progress throughout the year. With Bounty Meter, you can add and subtract bounties, view your total bounties earned this year, and display an interactive stats card to visualize your progress.
Home-page: https://github.com/720922/bountymeterPY
Download-URL: https://github.com/720922/bountymeterPY/archive/v1.0.0.zip
Author: 720922
License: GNU Affero General Public License v3.0
Keywords: recon,bugbounty,pentesting,utility,hacking
Classifier: Topic :: Security
Classifier: Operating System :: OS Independent
Classifier: Programming Language :: Python :: 3
License-File: LICENSE
Requires-Dist: progress
